{
    "created_time": "2020-11-01T05:47:50Z",
    "files": [
        {
            "attachment_folder": "",
            "attachments": [
            ],
            "created_time": "2020-11-01T08:15:32Z",
            "modified_time": "2020-11-02T07:45:48Z",
            "name": "01-移动端性能测试.md",
            "tags": [
            ]
        },
        {
            "attachment_folder": "",
            "attachments": [
            ],
            "created_time": "2020-11-04T01:03:32Z",
            "modified_time": "2020-11-04T10:31:13Z",
            "name": "02-移动端专项测试.md",
            "tags": [
            ]
        }
    ],
    "sub_directories": [
    ],
    "version": "1"
}
